{"data": {"latitude": {"0": 48.799, "1": 61.18, "2": 44.12, "3": 34.184, "4": 54.725, "5": 46.354, "6": 37.865, "7": 45.285, "8": 42.435, "9": 58.473}, "longitude": {"0": -123.056, "1": -149.105, "2": -71.195, "3": -83.561, "4": -101.861, "5": -84.303, "6": -119.538, "7": -111.383, "8": -75.065, "9": -113.815}, "location_id": {"0": "aa2370e7", "1": "383e7db0", "2": "a8623cd1", "3": "f8725f3e", "4": "1cac62ac", "5": "7097b7a4", "6": "f6e2fce8", "7": "9b96db86", "8": "3ab70e17", "9": "52071c07"}, "landsat_scene_id": {"0": null, "1": null, "2": null, "3": null, "4": null, "5": null, "6": null, "7": null, "8": null, "9": null}, "soilgrids_id": {"0": "aa2370e7", "1": null, "2": null, "3": null, "4": null, "5": null, "6": null, "7": null, "8": null, "9": null}}, "timestamp": "2024-12-17T01:08:51.661582", "name": "fetch_progress"}